__init__.py
paxutils/__init__.py
paxutils/path.py
paxutils-0.3.0.dist-info/licenses/LICENSE
paxutils-0.3.0.dist-info/METADATA
paxutils-0.3.0.dist-info/WHEEL
paxutils-0.3.0.dist-info/top_level.txt
paxutils-0.3.0.dist-info/RECORD
