Metadata-Version: 2.4
Name: paxutils
Version: 0.3.0
Summary: Miscellaneous utilities for PAX notebooks.
Author-email: Marc Parizeau <marc@parizeau.org>
License-Expression: MIT
Project-URL: Homepage, https://github.com/pax-ul/paxutils
Requires-Python: >=3.6
License-File: LICENSE
Requires-Dist: requests>=2.27.1
Requires-Dist: typing_extensions>=4.0.0
Dynamic: license-file
